README.md
setup.cfg
setup.py
journeypy/__init__.py
journeypy/__main__.py
journeypy.egg-info/PKG-INFO
journeypy.egg-info/SOURCES.txt
journeypy.egg-info/dependency_links.txt
journeypy.egg-info/entry_points.txt
journeypy.egg-info/requires.txt
journeypy.egg-info/top_level.txt
journeypy/core/__init__.py
journeypy/core/data/__init__.py
journeypy/core/data/runtime/Context.py
journeypy/core/data/runtime/__init__.py
journeypy/core/data/value/Values.py
journeypy/core/data/value/__init__.py
journeypy/core/data/variable/Variables.py
journeypy/core/data/variable/__init__.py
journeypy/core/io/IOs.py
journeypy/core/io/__init__.py
journeypy/template/Expressions.py
journeypy/template/Template.py
journeypy/template/__init__.py
journeypy/template/dsl.py
journeypy/template/text/Templates.py
journeypy/template/text/__init__.py